stanford_corenlp_python-3.3.9.dist-info/top_level.txt
stanford_corenlp_python-3.3.9.dist-info/DESCRIPTION.rst
stanford_corenlp_python-3.3.9.dist-info/metadata.json
stanford_corenlp_python-3.3.9.dist-info/RECORD
stanford_corenlp_python-3.3.9.dist-info/WHEEL
stanford_corenlp_python-3.3.9.dist-info/METADATA
corenlp/__init__.py
corenlp/corenlp.py
corenlp/progressbar.py
corenlp/default.properties
corenlp/client.py
