Metadata-Version: 2.0
Name: stanford-corenlp-python
Version: 3.3.9
Summary: A Stanford Core NLP wrapper (wordseer fork)
Home-page: https://github.com/Wordseer/stanford-corenlp-python
Author: Hiroyoshi Komatsu, Dustin Smith, Aditi Muralidharan
Author-email: aditi.shrikumar@gmail.com
License: UNKNOWN
Platform: UNKNOWN
Classifier: License :: OSI Approved :: GNU General Public License v2 or later (GPLv2+)
Classifier: Programming Language :: Python
Requires-Dist: unidecode (>=0.04.12)
Requires-Dist: xmltodict (>=0.4.6)
Requires-Dist: pexpect (>=2.4)
